caliz/__init__.py
caliz/calculator.py
caliz-0.0.2.dist-info/LICENSE
caliz-0.0.2.dist-info/METADATA
caliz-0.0.2.dist-info/WHEEL
caliz-0.0.2.dist-info/top_level.txt
caliz-0.0.2.dist-info/RECORD
