Metadata-Version: 2.1
Name: caliz
Version: 0.0.2
Summary: A small calculator package program built with tkinter python
Home-page: https://github.com/pypa/sampleproject
Author: Anamol Dhakal, MD Rajaul Aansari, Sweing Nakarmi
Author-email: anmoldkl971@gmail.com
Project-URL: Bug Tracker, https://github.com/pypa/sampleproject/issues
Classifier: Programming Language :: Python :: 3
Classifier: License :: OSI Approved :: MIT License
Classifier: Operating System :: OS Independent
Requires-Python: >=3.6
License-File: LICENSE
